{"m5":{"nameMatch":"-","deal":"","teamName":["LS Vainqueur","ひとりはみんなのために。"],"state":"beforeTheWar"},"m2":{"nameMatch":"-","deal":"","teamName":["クラクラチャンネルOMINÖS","All My Turn"],"state":"beforeTheWar"},"m3":{"nameMatch":"-","deal":{"date":"2024 年 7 月 27 日 （土）","time":"17:00","prep_time":"4h","battle_time":"24h","send":"neo","size":"20v20","unixTime":1722067200},"teamName":["殺戮卍協会","無課金弱者連合NEO"],"state":"beforeTheWar"},"m4":{"nameMatch":"-","deal":"","teamName":["ネコふんじゃったΣ(￣。￣ﾉ)","1LegioN's Orbit"],"state":"beforeTheWar"},"m1":{"nameMatch":"-","deal":"","teamName":["UWS 69","てぃぁら✩.*˚♡"],"state":"beforeTheWar"},"m6":{"nameMatch":"-","deal":"","teamName":["関西クラクラ倶楽部","SAMURAI"],"state":"beforeTheWar"}}